kaparoo/__about__.py
kaparoo/__init__.py
kaparoo/py.typed
kaparoo/beartype/__init__.py
kaparoo/beartype/numerics.py
kaparoo/filesystem/__init__.py
kaparoo/filesystem/exceptions.py
kaparoo/filesystem/path.py
kaparoo/filesystem/types.py
kaparoo/utils/__init__.py
kaparoo/utils/optional.py
kaparoo/utils/singleton.py
kaparoo/utils/types.py
kaparoo_python_package-0.3.0.dist-info/METADATA
kaparoo_python_package-0.3.0.dist-info/WHEEL
kaparoo_python_package-0.3.0.dist-info/licenses/LICENSE
kaparoo_python_package-0.3.0.dist-info/RECORD
